llm_anthropic.py
llm_anthropic-0.20.dist-info/licenses/LICENSE
llm_anthropic-0.20.dist-info/METADATA
llm_anthropic-0.20.dist-info/WHEEL
llm_anthropic-0.20.dist-info/entry_points.txt
llm_anthropic-0.20.dist-info/top_level.txt
llm_anthropic-0.20.dist-info/RECORD
