Metadata-Version: 2.4
Name: llm-anthropic
Version: 0.20
Summary: LLM access to models by Anthropic, including the Claude series
Author: Simon Willison
License: Apache-2.0
Project-URL: Homepage, https://github.com/simonw/llm-anthropic
Project-URL: Changelog, https://github.com/simonw/llm-anthropic/releases
Project-URL: Issues, https://github.com/simonw/llm-anthropic/issues
Project-URL: CI, https://github.com/simonw/llm-anthropic/actions
Classifier: License :: OSI Approved :: Apache Software License
License-File: LICENSE
Requires-Dist: llm>=0.26
Requires-Dist: anthropic>=0.48.0
Provides-Extra: test
Requires-Dist: pytest; extra == "test"
Requires-Dist: pytest-recording; extra == "test"
Requires-Dist: pytest-asyncio; extra == "test"
Requires-Dist: cogapp; extra == "test"
Dynamic: license-file
